[{"year":2001,"crime_per_citizen":0.0118521273},{"year":2002,"crime_per_citizen":0.0140465357},{"year":2003,"crime_per_citizen":0.0140758528},{"year":2004,"crime_per_citizen":0.0153809828},{"year":2005,"crime_per_citizen":0.0142974686},{"year":2006,"crime_per_citizen":0.0127115748},{"year":2007,"crime_per_citizen":0.0136221702},{"year":2008,"crime_per_citizen":0.0129597122},{"year":2009,"crime_per_citizen":0.0141869182},{"year":2010,"crime_per_citizen":0.0126599189},{"year":2011,"crime_per_citizen":0.0130851282},{"year":2012,"crime_per_citizen":0.0130706944},{"year":2013,"crime_per_citizen":0.0127769694},{"year":2014,"crime_per_citizen":0.0117686259},{"year":2015,"crime_per_citizen":0.0106452406},{"year":2016,"crime_per_citizen":0.0104429907},{"year":2017,"crime_per_citizen":0.0101912953},{"year":2018,"crime_per_citizen":0.0094114515},{"year":2019,"crime_per_citizen":0.0086097621},{"year":2020,"crime_per_citizen":0.0081724506},{"year":2021,"crime_per_citizen":0.0077340208},{"year":2022,"crime_per_citizen":0.0084408814},{"year":2023,"crime_per_citizen":0.008402026},{"year":2024,"crime_per_citizen":0.0079739212},{"year":2025,"crime_per_citizen":0.0076519106},{"year":2026,"crime_per_citizen":0.0073282094},{"year":2027,"crime_per_citizen":0.0070028043},{"year":2028,"crime_per_citizen":0.0066756819},{"year":2029,"crime_per_citizen":0.0063468284},{"year":2030,"crime_per_citizen":0.0060162301},{"year":2031,"crime_per_citizen":0.0056838732},{"year":2032,"crime_per_citizen":0.0053497434},{"year":2033,"crime_per_citizen":0.0050138266},{"year":2034,"crime_per_citizen":0.0046761085},{"year":2035,"crime_per_citizen":0.0043365745},{"year":2036,"crime_per_citizen":0.0039952098},{"year":2037,"crime_per_citizen":0.0036519997},{"year":2038,"crime_per_citizen":0.0033069292},{"year":2039,"crime_per_citizen":0.0029599831},{"year":2040,"crime_per_citizen":0.002611146}]